polito_dl/__init__.py
polito_dl/auth.py
polito_dl/cli.py
polito_dl/client.py
polito_dl/parsing.py
polito_dl/scraping.py
polito_dl-2.0.0a0.dist-info/LICENSE
polito_dl-2.0.0a0.dist-info/METADATA
polito_dl-2.0.0a0.dist-info/WHEEL
polito_dl-2.0.0a0.dist-info/entry_points.txt
polito_dl-2.0.0a0.dist-info/top_level.txt
polito_dl-2.0.0a0.dist-info/RECORD
