Metadata-Version: 2.1
Name: polito-dl
Version: 2.0.0a0
Summary: Command-line tool and library to download Polytechnic of Turin's online lessons from didattica.polito.it
Home-page: https://github.com/glumia/polito_dl
Author: Giuseppe Lumia
Author-email: glumia@protonmail.com
License: GPLv3
Keywords: polito,politecnico,torino
Platform: UNKNOWN
Classifier: Development Status :: 3 - Alpha
Classifier: Programming Language :: Python :: 3
Classifier: License :: OSI Approved :: GNU General Public License v3 (GPLv3)
Classifier: Operating System :: OS Independent
Requires-Dist: requests
Requires-Dist: bs4
Requires-Dist: click
